CMakeLists.txt
LICENSE
MANIFEST.in
README.rst
VERSION
setup.py
./pyxmolpp2/py.typed
./tools/__init__.py
./tools/print_version_number.py
./tools/run-benchmark.py
./tools/write_version_info.py
bindings/CMakeLists.txt
bindings/src/TorsionAngle.cpp
bindings/src/TorsionAngle.h
bindings/src/base.cpp
bindings/src/base.h
bindings/src/init.cpp
bindings/src/init.h
bindings/src/iterator-helpers.h
bindings/src/pyxmolpp2.cpp
bindings/src/repr-helpers.h
bindings/src/algo/algo.cpp
bindings/src/algo/algo.h
bindings/src/geom/AngleValue.cpp
bindings/src/geom/AngleValue.h
bindings/src/geom/Transformation3d.cpp
bindings/src/geom/Transformation3d.h
bindings/src/geom/UnitCell.cpp
bindings/src/geom/UnitCell.h
bindings/src/geom/XYZ.cpp
bindings/src/geom/XYZ.h
bindings/src/io/AmberNetCDF.cpp
bindings/src/io/AmberNetCDF.h
bindings/src/io/GromacsXtcFile.cpp
bindings/src/io/GromacsXtcFile.h
bindings/src/io/PdbFile.cpp
bindings/src/io/PdbFile.h
bindings/src/io/TrjtoolDatFile.cpp
bindings/src/io/TrjtoolDatFile.h
bindings/src/pipe/pipe.cpp
bindings/src/pipe/pipe.h
bindings/src/predicates/predicates.cpp
bindings/src/predicates/predicates.h
bindings/src/proxy/references.cpp
bindings/src/proxy/references.h
bindings/src/proxy/selections.cpp
bindings/src/proxy/selections.h
bindings/src/proxy/spans.cpp
bindings/src/proxy/spans.h
bindings/src/proxy/to_pdb_shortcuts.h
bindings/src/trajectory/trajectory.cpp
bindings/src/trajectory/trajectory.h
cmake/FindNetCDF.cmake
cmake/WriteVersionInfo.cmake
external/GSL/.clang-format
external/GSL/.gitignore
external/GSL/.travis.yml
external/GSL/CMakeLists.txt
external/GSL/CMakeSettings.json
external/GSL/CONTRIBUTING.md
external/GSL/GSL.natvis
external/GSL/LICENSE
external/GSL/README.md
external/GSL/ThirdPartyNotices.txt
external/GSL/appveyor.yml
external/GSL/azure-pipelines.yml
external/GSL/.github/workflows/android.yml
external/GSL/.github/workflows/ios.yml
external/GSL/cmake/guidelineSupportLibrary.cmake
external/GSL/include/gsl/algorithm
pyxmolpp2.egg-info/PKG-INFO
pyxmolpp2.egg-info/SOURCES.txt
pyxmolpp2.egg-info/dependency_links.txt
pyxmolpp2.egg-info/not-zip-safe
pyxmolpp2.egg-info/requires.txt
pyxmolpp2.egg-info/top_level.txt
