Metadata-Version: 2.1
Name: pyxmolpp2
Version: 2.0.2
Summary: Utils for processing MD
Home-page: https://github.com/sizmailov/pyxmolpp2
Author: Sergei Izmailov
Author-email: sergei.a.izmailov@gmail.com
Classifier: License :: OSI Approved :: MIT License
License-File: LICENSE
